{
  "id": "3284581",
  "name": "qk_blog",
  "font_family": "iconfont",
  "css_prefix_text": "icon-",
  "description": "",
  "glyphs": [
    {
      "icon_id": "577350",
      "name": "朋友",
      "font_class": "pengyou",
      "unicode": "e746",
      "unicode_decimal": 59206
    },
    {
      "icon_id": "1447730",
      "name": "页面",
      "font_class": "yemian",
      "unicode": "e615",
      "unicode_decimal": 58901
    },
    {
      "icon_id": "2675009",
      "name": "首页",
      "font_class": "shouye",
      "unicode": "e62e",
      "unicode_decimal": 58926
    },
    {
      "icon_id": "5192249",
      "name": "咖啡",
      "font_class": "kafei",
      "unicode": "e602",
      "unicode_decimal": 58882
    },
    {
      "icon_id": "7817216",
      "name": "分类",
      "font_class": "fenlei",
      "unicode": "e611",
      "unicode_decimal": 58897
    },
    {
      "icon_id": "17608625",
      "name": "艾特",
      "font_class": "aite",
      "unicode": "e60d",
      "unicode_decimal": 58893
    },
    {
      "icon_id": "19418425",
      "name": "github",
      "font_class": "github",
      "unicode": "e728",
      "unicode_decimal": 59176
    },
    {
      "icon_id": "853006",
      "name": "树叶",
      "font_class": "shuye",
      "unicode": "e6ac",
      "unicode_decimal": 59052
    },
    {
      "icon_id": "924719",
      "name": "文章",
      "font_class": "wenzhang",
      "unicode": "e624",
      "unicode_decimal": 58916
    },
    {
      "icon_id": "21591052",
      "name": "归档审计平台",
      "font_class": "guidangshenjipingtai",
      "unicode": "e69b",
      "unicode_decimal": 59035
    },
    {
      "icon_id": "13084027",
      "name": "城堡@2x",
      "font_class": "chengbaox",
      "unicode": "e6bf",
      "unicode_decimal": 59071
    }
  ]
}
